LICENSE
README.md
setup.cfg
setup.py
src/fexception/__init__.py
src/fexception/common.py
src/fexception/fexception.py
src/fexception/formatter.py
src/fexception/util.py
src/fexception.egg-info/PKG-INFO
src/fexception.egg-info/SOURCES.txt
src/fexception.egg-info/dependency_links.txt
src/fexception.egg-info/not-zip-safe
src/fexception.egg-info/requires.txt
src/fexception.egg-info/top_level.txt