Metadata-Version: 2.1
Name: fexception
Version: 0.3.17
Summary: fexception is designed to provide cleaner useable exceptions.
Home-page: https://github.com/IncognitoCoding/fexception
Author: IncognitoCoding
License: MIT
Platform: any
Classifier: Development Status :: 4 - Beta
Classifier: Programming Language :: Python :: 3
Classifier: License :: OSI Approved :: MIT License
Classifier: Operating System :: POSIX :: Linux
Classifier: Operating System :: Microsoft :: Windows
Provides-Extra: testing
License-File: LICENSE
